CHANGELOG.txt
MANIFEST.in
README.rst
requirements.txt
setup.py
easy_chrome_driver/__init__.py
easy_chrome_driver.egg-info/PKG-INFO
easy_chrome_driver.egg-info/SOURCES.txt
easy_chrome_driver.egg-info/dependency_links.txt
easy_chrome_driver.egg-info/requires.txt
easy_chrome_driver.egg-info/top_level.txt
tests/test_easy_chrome_driver.py
tests/proxy_driver/log.txt
tests/proxy_driver/user_data/chrome_shutdown_ms.txt