Metadata-Version: 1.1
Name: easy-chrome-driver
Version: 0.0.2
Summary: Abstraction for chrome driver for easy modifications
Home-page: https://github.com/vaibhavkpatel1/easy_chrome_driver
Author: Vaibhavkumar Patel
Author-email: vaibhavkpatel1@gmail.com
License: MIT
Keywords: easy_chromedriver chrome_driver webdriver proxy_driver
Platform: UNKNOWN
Classifier: Development Status :: 5 - Production/Stable
Classifier: Intended Audience :: Developers
Classifier: Operating System :: POSIX :: Linux
Classifier: Operating System :: Microsoft :: Windows
Classifier: License :: OSI Approved :: MIT License
Classifier: Programming Language :: Python :: 3
